CHANGES.txt
README.md
README.txt
buildout.cfg
setup.cfg
setup.py
src/netsight/__init__.py
src/netsight.aspxauthplugin.egg-info/PKG-INFO
src/netsight.aspxauthplugin.egg-info/SOURCES.txt
src/netsight.aspxauthplugin.egg-info/dependency_links.txt
src/netsight.aspxauthplugin.egg-info/entry_points.txt
src/netsight.aspxauthplugin.egg-info/namespace_packages.txt
src/netsight.aspxauthplugin.egg-info/not-zip-safe
src/netsight.aspxauthplugin.egg-info/paster_plugins.txt
src/netsight.aspxauthplugin.egg-info/requires.txt
src/netsight.aspxauthplugin.egg-info/top_level.txt
src/netsight/aspxauthplugin/__init__.py
src/netsight/aspxauthplugin/install.py
src/netsight/aspxauthplugin/plugin.py
src/netsight/aspxauthplugin/testing.py
src/netsight/aspxauthplugin/browser/__init__.py
src/netsight/aspxauthplugin/tests/__init__.py
src/netsight/aspxauthplugin/tests/test_plugin.py