Metadata-Version: 1.0
Name: netsight.aspxauthplugin
Version: 1.0.3
Summary: PAS Plugin for Zope/Plone that can authenticate a user via the .NET ASPXAUTH cookie
Home-page: http://svn.plone.org/svn/collective/
Author: Matt Hamilton
Author-email: matth@netsight.co.uk
License: gpl
Platform: UNKNOWN
Classifier: Environment :: Web Environment
Classifier: Framework :: Plone
Classifier: Operating System :: OS Independent
Classifier: Programming Language :: Python
Classifier: Programming Language :: Python :: 2.6
Classifier: Topic :: Software Development :: Libraries :: Python Modules
